cgg/__init__.py
cgg-0.4.9.dist-info/entry_points.txt
cgg-0.4.9.dist-info/LICENSE
cgg-0.4.9.dist-info/WHEEL
cgg-0.4.9.dist-info/METADATA
cgg-0.4.9.dist-info/RECORD
