Metadata-Version: 2.1
Name: cgg
Version: 0.4.9
Summary: cgg is a short form of call gguf model/file; cgg is a cmd-based app built on gguf-connector, which allows users interacting with large language model (i.e., chatgpt) via a simple command without coding a long long syntax
Author-email: calcuis <info@calcu.io>
Classifier: License :: OSI Approved :: MIT License
Requires-Dist: gguf-connector >=2.9.0
Project-URL: Community, https://www.reddit.com/r/gguf
Project-URL: Homepage, https://gguf.us
Project-URL: Issues, https://github.com/calcuis/cgg/issues
Project-URL: Repository, https://github.com/calcuis/cgg
